AUTHORS
LICENSE
LICENSE.pyevent
MANIFEST.in
README.rst
TODO
changelog.rst
fetch_libevent.py
setup.cfg
setup.py
doc/Makefile
doc/community.rst
doc/conf.py
doc/contents.rst
doc/generate_rst.py
doc/gevent.core.rst
doc/gevent.event.rst
doc/gevent.hub.rst
doc/gevent.queue.rst
doc/gevent.rst
doc/intro.rst
doc/make.bat
doc/mysphinxext.py
doc/networking.rst
doc/reference.rst
doc/servers.rst
doc/synchronization.rst
doc/_templates/layout.html
examples/concurrent_download.py
examples/dns_mass_resolve.py
examples/echoserver.py
examples/geventsendfile.py
examples/httpserver.py
examples/processes.py
examples/server.crt
examples/server.key
examples/webproxy.py
examples/webpy.py
examples/wsgiserver.py
examples/wsgiserver_ssl.py
examples/webchat/README
examples/webchat/__init__.py
examples/webchat/manage.py
examples/webchat/run.py
examples/webchat/settings.py
examples/webchat/urls.py
examples/webchat/chat/__init__.py
examples/webchat/chat/views.py
examples/webchat/static/chat.css
examples/webchat/static/chat.js
examples/webchat/templates/404.html
examples/webchat/templates/500.html
examples/webchat/templates/index.html
examples/webchat/templates/message.html
gevent/__init__.py
gevent/backdoor.py
gevent/baseserver.py
gevent/core.c
gevent/core.pyx
gevent/coros.py
gevent/dns.py
gevent/evbuffer.pxi
gevent/evdns.pxi
gevent/event.py
gevent/evhttp.pxi
gevent/greenlet.py
gevent/http.py
gevent/httplib.py
gevent/hub.py
gevent/libevent.h
gevent/local.py
gevent/monkey.py
gevent/pool.py
gevent/pywsgi.py
gevent/queue.py
gevent/rawgreenlet.py
gevent/select.py
gevent/server.py
gevent/socket.py
gevent/ssl.py
gevent/sslold.py
gevent/thread.py
gevent/timeout.py
gevent/util.py
gevent/win32util.py
gevent/wsgi.py
greentest/badcert.pem
greentest/badkey.pem
greentest/bench_sendall.py
greentest/bench_sleep0.py
greentest/bench_spawn.py
greentest/greentest.py
greentest/helper.py
greentest/https_svn_python_org_root.pem
greentest/keycert.pem
greentest/lock_tests.py
greentest/mysubprocess.py
prat_gevent.egg-info/PKG-INFO
prat_gevent.egg-info/SOURCES.txt
prat_gevent.egg-info/dependency_links.txt
prat_gevent.egg-info/requires.txt
prat_gevent.egg-info/top_level.txt