Metadata-Version: 1.0
Name: prat-gevent
Version: 0.13.6
Summary: Prat fork of Denis Beilenko's Python network library that uses greenlet and libevent for easy and scalable concurrency
Home-page: https://github.com/bkad/gevent
Author: Kevin Le
Author-email: solnovus@gmail.com
License: UNKNOWN
Platform: UNKNOWN
Classifier: License :: OSI Approved :: MIT License
Classifier: Programming Language :: Python :: 2.4
Classifier: Programming Language :: Python :: 2.5
Classifier: Programming Language :: Python :: 2.6
Classifier: Programming Language :: Python :: 2.7
Classifier: Operating System :: MacOS :: MacOS X
Classifier: Operating System :: POSIX
Classifier: Operating System :: Microsoft :: Windows
Classifier: Topic :: Internet
Classifier: Topic :: Software Development :: Libraries :: Python Modules
Classifier: Intended Audience :: Developers
Classifier: Development Status :: 4 - Beta
